{
  "race_id": "Wolverhampton_1730_20260310",
  "race_meta": {
    "track": "Wolverhampton",
    "time": "17:30",
    "date": "2026-03-10",
    "race_name": "Midnite Are Upping The Betting Game Classified Stakes (Div 1)",
    "class": "6",
    "going": "Tapeta (Standard)"
  },
  "timestamp": "2026-03-12T18:33:31.687381",
  "official_result": {
    "winner": "Saachi",
    "order": [
      "Saachi",
      "Gemini Man",
      "Muhib"
    ]
  },
  "analysis": {
    "ruby": {
      "title": "Probability Analysis",
      "insight": "Actual winner saachi was not in model's ranked horses. Model focused too heavily on pre-race favorites. Top prediction was Gemini Man (IRE) with 48.0% confidence."
    },
    "keenan": {
      "title": "Forecast & Distribution",
      "insight": "Top forecast prediction was Gemini Man (IRE) > Virtual Hug (IRE), but actual result was Saachi > Gemini Man. Distribution model underestimated variance in placing combinations."
    },
    "mordin": {
      "title": "Market Alignment",
      "insight": "Actual winner not found in market analysis. Market dynamics shifted unexpectedly from pre-race state."
    }
  }
}