{
  "race_id": "ChelmsfordCity_2000_20260307",
  "meta": {
    "track": "Chelmsford City",
    "time": "20:00",
    "date": "2026-03-07",
    "race_name": "For The Love Of Horses Handicap",
    "class": "6",
    "going": "Standard"
  },
  "analysis": {
    "ruby": {
      "race_id": "ChelmsfordCity_2000_20260307",
      "race_volatility": "medium",
      "rankings": [
        {
          "name": "Desdemona",
          "win_probability": 32,
          "place_probability": 65,
          "fair_odds": 3.13,
          "key_positive_factors": [
            "Consistent placement history"
          ],
          "key_risks": []
        },
        {
          "name": "Buraback",
          "win_probability": 28,
          "place_probability": 60,
          "fair_odds": 3.57,
          "key_positive_factors": [],
          "key_risks": []
        },
        {
          "name": "Sir Rodneyredblood",
          "win_probability": 13,
          "place_probability": 40,
          "fair_odds": 7.69,
          "key_positive_factors": [],
          "key_risks": []
        },
        {
          "name": "Top Star",
          "win_probability": 8,
          "place_probability": 30,
          "fair_odds": 12.5,
          "key_positive_factors": [
            "Consistent trainer",
            "Favorable odds"
          ],
          "key_risks": []
        },
        {
          "name": "Battle Point",
          "win_probability": 6,
          "place_probability": 25,
          "fair_odds": 16.67,
          "key_positive_factors": [],
          "key_risks": []
        },
        {
          "name": "Hi Hoh Tonto",
          "win_probability": 5,
          "place_probability": 20,
          "fair_odds": 20,
          "key_positive_factors": [],
          "key_risks": [
            "Inferred Jockey Trainer due to missing data"
          ]
        },
        {
          "name": "Master Zack",
          "win_probability": 4,
          "place_probability": 15,
          "fair_odds": 25,
          "key_positive_factors": [],
          "key_risks": [
            "Inferred Jockey Trainer due to missing data"
          ]
        },
        {
          "name": "Daley T",
          "win_probability": 4,
          "place_probability": 10,
          "fair_odds": 25,
          "key_positive_factors": [],
          "key_risks": []
        }
      ],
      "feature_weight_summary": {
        "performance": 0.5,
        "tactics": 0.2,
        "trainer_jockey": 0.15,
        "conditions": 0.1,
        "market": 0.05
      }
    },
    "keenan": {
      "race_id": "ChelmsfordCity_2000_20260307",
      "certainty_level": "medium",
      "most_probable_winner": {
        "horse": "Desdemona",
        "probability": 0.32
      },
      "forecast_top_3": [
        {
          "combination": "Desdemona > Buraback",
          "probability": 0.0896
        },
        {
          "combination": "Buraback > Desdemona",
          "probability": 0.0896
        },
        {
          "combination": "Desdemona > Sir Rodneyredblood",
          "probability": 0.0416
        }
      ],
      "tricast_top_3": [
        {
          "combination": "Desdemona > Buraback > Sir Rodneyredblood",
          "probability": 0.011648
        },
        {
          "combination": "Desdemona > Buraback > Top Star",
          "probability": 0.007168
        },
        {
          "combination": "Buraback > Desdemona > Sir Rodneyredblood",
          "probability": 0.011648
        }
      ],
      "distribution_notes": [
        "Forecast and Tricast probabilities are estimates based on conditional proportional allocation.",
        "Medium certainty level. Competitive field with slight advantage to Desdemona due to placement history."
      ]
    },
    "mordin": {
      "race_id": "ChelmsfordCity_2000_20260307",
      "market_comparison": [
        {
          "horse": "Desdemona",
          "model_probability": 0.32,
          "market_implied_probability": 0.29,
          "divergence": 0.03,
          "divergence_class": "Mild Divergence"
        },
        {
          "horse": "Buraback",
          "model_probability": 0.28,
          "market_implied_probability": 0.43,
          "divergence": -0.15,
          "divergence_class": "Strong Divergence"
        },
        {
          "horse": "Sir Rodneyredblood",
          "model_probability": 0.13,
          "market_implied_probability": 0.13,
          "divergence": 0,
          "divergence_class": "Neutral"
        },
        {
          "horse": "Top Star",
          "model_probability": 0.08,
          "market_implied_probability": 0.09,
          "divergence": -0.01,
          "divergence_class": "Neutral"
        },
        {
          "horse": "Battle Point",
          "model_probability": 0.06,
          "market_implied_probability": 0.05,
          "divergence": 0.01,
          "divergence_class": "Neutral"
        },
        {
          "horse": "Hi Hoh Tonto",
          "model_probability": 0.05,
          "market_implied_probability": 0.1,
          "divergence": -0.05,
          "divergence_class": "Neutral"
        },
        {
          "horse": "Master Zack",
          "model_probability": 0.04,
          "market_implied_probability": 0.1,
          "divergence": -0.06,
          "divergence_class": "Neutral"
        },
        {
          "horse": "Daley T",
          "model_probability": 0.04,
          "market_implied_probability": 0.05,
          "divergence": -0.01,
          "divergence_class": "Neutral"
        }
      ],
      "model_confidence_flag": "None",
      "calibration_notes": [
        "Low Confidence , the Model exhibits signals for Market's confidence on Buraback but strong placement signals for Desdemona."
      ]
    }
  }
}
