{"race_id": "ChelmsfordAW_1649_20260312", "meta": {"track": "Chelmsford (AW)", "time": "16:49", "date": "2026-03-12", "race_name": "bettingsites.co.uk UK Betting Sites Amateur Jockeys' Handicap", "class": "Class 6", "going": "Standard", "distance": "1m2f", "prize": "\u00a33,477"}, "analysis": {"ruby": {"race_id": "ChelmsfordAW_1649_20260312", "rankings": [{"name": "Bronte Beach", "win_probability": 0.3, "place_probability": 0.6, "fair_odds": 3.33, "key_positive_factors": ["Fastest final 2f split", "Promising handicap debut", "Longer trip suits breeding"], "key_risks": ["Seventh in previous runs", "High initial odds"]}, {"name": "Beachborough Girl", "win_probability": 0.25, "place_probability": 0.55, "fair_odds": 4.0, "key_positive_factors": ["Course and distance winner", "Consistent recent form", "Experienced rider"], "key_risks": ["Limited recent success", "Moderate official rating"]}, {"name": "Hes Our Cracker", "win_probability": 0.15, "place_probability": 0.45, "fair_odds": 6.67, "key_positive_factors": ["Improved recent performance", "Unexposed 4yo", "Weighted to improve"], "key_risks": ["Limited race history", "Amateur jockey"]}, {"name": "Silkies Sib", "win_probability": 0.12, "place_probability": 0.4, "fair_odds": 8.33, "key_positive_factors": ["Two wins this winter", "Consistent with visor", "Course and distance winner"], "key_risks": ["Inexperienced amateur jockey", "Slightly worse weights"]}, {"name": "Jack Andrea", "win_probability": 0.08, "place_probability": 0.3, "fair_odds": 12.5, "key_positive_factors": ["First win after 19 attempts", "New yard potential", "Course and distance experience"], "key_risks": ["Limited success", "Amateur jockey"]}, {"name": "King Of The Dance", "win_probability": 0.05, "place_probability": 0.25, "fair_odds": 20.0, "key_positive_factors": ["Reliable in 2025", "Promising recent return", "Handicap winner"], "key_risks": ["Stamina questions", "Stepping up in distance"]}, {"name": "Crafter", "win_probability": 0.03, "place_probability": 0.15, "fair_odds": 33.0, "key_positive_factors": ["Dangerous mark", "New blinkers added"], "key_risks": ["No winter form", "Amateur jockey", "Limited recent success"]}, {"name": "Versatile", "win_probability": 0.02, "place_probability": 0.1, "fair_odds": 50.0, "key_positive_factors": ["Previously placed off higher mark", "Down in weights"], "key_risks": ["Slow starts", "Poor recent form", "Amateur jockey"]}]}, "keenan": {"most_probable_winner": {"horse": "Bronte Beach", "probability": 0.3}, "forecast_top_3": [{"combination": "Bronte Beach > Beachborough Girl", "probability": 0.18}, {"combination": "Bronte Beach > Hes Our Cracker", "probability": 0.15}], "tricast_top_3": [{"combination": "Bronte Beach > Beachborough Girl > Hes Our Cracker", "probability": 0.11}], "pace_analysis": {"type": "MODERATE", "leader": "Silkies Sib", "insight": "Silkies Sib's early pace could create tactical challenges that benefit horses with strong finishing kicks"}}, "mordin": {"race_id": "ChelmsfordAW_1649_20260312", "market_comparison": [{"horse": "Bronte Beach", "model_probability": 0.3, "market_implied_probability": null, "divergence": null, "adjustment_reason": "No market odds available"}, {"horse": "Beachborough Girl", "model_probability": 0.25, "market_implied_probability": null, "divergence": null, "adjustment_reason": "No market odds available"}, {"horse": "Hes Our Cracker", "model_probability": 0.15, "market_implied_probability": null, "divergence": null, "adjustment_reason": "No market odds available"}, {"horse": "Silkies Sib", "model_probability": 0.12, "market_implied_probability": null, "divergence": null, "adjustment_reason": "No market odds available"}, {"horse": "Jack Andrea", "model_probability": 0.08, "market_implied_probability": null, "divergence": null, "adjustment_reason": "No market odds available"}, {"horse": "King Of The Dance", "model_probability": 0.05, "market_implied_probability": null, "divergence": null, "adjustment_reason": "No market odds available"}, {"horse": "Crafter", "model_probability": 0.03, "market_implied_probability": null, "divergence": null, "adjustment_reason": "No market odds available"}, {"horse": "Versatile", "model_probability": 0.02, "market_implied_probability": null, "divergence": null, "adjustment_reason": "No market odds available"}], "model_confidence_flag": "Low", "calibration_notes": ["No market intelligence available", "Insufficient market data"]}}}
