{"race_id": "Doncaster_1422_20260313", "meta": {"track": "Doncaster", "time": "14:22", "date": "2026-03-13", "race_name": "Virgin Bet Novices' Handicap Chase (Go North Forgive 'N Forget Series Qualifier) (GBB Race)", "class": "Class 4", "going": "Good", "distance": "2m3f31y", "prize": "\u00a34,700"}, "analysis": {"ruby": {"race_id": "Doncaster_1422_20260313", "rankings": [{"name": "Cuban Court", "win_probability": 0.4, "place_probability": 0.7, "fair_odds": 2.5, "key_positive_factors": ["Highest RPR", "Recent course and distance win", "Readily won last two races", "Stable in good form"], "key_risks": ["8lb weight increase", "Older horse"]}, {"name": "Lightning Flash", "win_probability": 0.3, "place_probability": 0.6, "fair_odds": 3.33, "key_positive_factors": ["Winning start over fences", "Potentially improving", "Break might have refreshed", "Competitive rating"], "key_risks": ["Falling at Ludlow", "Mistakes in previous runs", "Inconsistent form"]}, {"name": "Whatyouwaitingfor", "win_probability": 0.2, "place_probability": 0.5, "fair_odds": 5.0, "key_positive_factors": ["Reliable hurdler", "Good second in previous handicap", "New yard potentially improving", "Youngest horse"], "key_risks": ["No chase history", "No established RPR in chasing", "Yard change"]}]}, "keenan": {"most_probable_winner": {"horse": "Cuban Court", "probability": 0.4}, "forecast_top_3": [{"combination": "Cuban Court > Lightning Flash", "probability": 0.22}, {"combination": "Cuban Court > Whatyouwaitingfor", "probability": 0.18}], "tricast_top_3": [{"combination": "Cuban Court > Lightning Flash > Whatyouwaitingfor", "probability": 0.12}], "pace_analysis": {"type": "MODERATE", "leader": "Lightning Flash", "insight": "Lightning Flash's potential early pace could create tactical challenges that benefit horses with strong finishing capabilities"}}, "mordin": {"race_id": "Doncaster_1422_20260313", "market_comparison": [{"horse": "Cuban Court", "model_probability": 0.4, "market_implied_probability": null, "divergence": null, "adjustment_reason": "Strong market support, odds around 6/4, recent 13-length victory at same track"}, {"horse": "Lightning Flash", "model_probability": 0.3, "market_implied_probability": null, "divergence": null, "adjustment_reason": "No market odds available"}, {"horse": "Whatyouwaitingfor", "model_probability": 0.2, "market_implied_probability": null, "divergence": null, "adjustment_reason": "Market support with odds around 4/1 to 9/2, debut for Old Gold Racing and Charlie Longsdon"}], "model_confidence_flag": "Medium", "calibration_notes": ["Partial market sentiment available", "Strong support for Cuban Court and Whatyouwaitingfor"]}}}
