{"race_id": "Doncaster_1342_20260313", "meta": {"track": "Doncaster", "time": "13:42", "date": "2026-03-13", "race_name": "Virgin Bet Novices' Hurdle (GBB Race)", "class": "Class 4", "going": "Good", "distance": "2m128y", "prize": "\u00a35,446"}, "analysis": {"ruby": {"race_id": "Doncaster_1342_20260313", "rankings": [{"name": "Count Of Vendome", "win_probability": 0.45, "place_probability": 0.7, "fair_odds": 2.2, "key_positive_factors": ["Highest RPR", "Dual bumper winner", "Course and distance winner", "Promising start over hurdles", "Very good second at Bangor"], "key_risks": ["Relatively new to hurdling"]}, {"name": "Lewisham Grove", "win_probability": 0.25, "place_probability": 0.55, "fair_odds": 4.0, "key_positive_factors": ["Won at Newcastle", "Cheekpieces added", "Not disgraced in previous races", "Consistent performer"], "key_risks": ["Inconsistent recent form", "Last in previous race"]}, {"name": "Corsican Caper", "win_probability": 0.1, "place_probability": 0.35, "fair_odds": 10.0, "key_positive_factors": ["Flat race winner", "Experienced horse"], "key_risks": ["Tailed off in hurdles debut", "Below par on recent Flat races", "Lowest RPR"]}, {"name": "Its Party Time", "win_probability": 0.05, "place_probability": 0.2, "fair_odds": 20.0, "key_positive_factors": ["Frame in Irish point", "Young horse"], "key_risks": ["Pulled up in novice hurdles", "No racing history", "Significantly more required"]}]}, "keenan": {"most_probable_winner": {"horse": "Count Of Vendome", "probability": 0.45}, "forecast_top_3": [{"combination": "Count Of Vendome > Lewisham Grove", "probability": 0.22}, {"combination": "Count Of Vendome > Corsican Caper", "probability": 0.18}], "tricast_top_3": [{"combination": "Count Of Vendome > Lewisham Grove > Corsican Caper", "probability": 0.12}], "pace_analysis": {"type": "MODERATE", "leader": "Lewisham Grove", "insight": "Lewisham Grove's potential early pace could create tactical challenges that benefit horses with strong finishing capabilities"}}, "mordin": {"race_id": "Doncaster_1342_20260313", "market_comparison": [{"horse": "Count Of Vendome", "model_probability": 0.45, "market_implied_probability": null, "divergence": null, "adjustment_reason": "Very strong market support, odds at 4/11 to 8/15, recent second at Bangor"}, {"horse": "Lewisham Grove", "model_probability": 0.25, "market_implied_probability": null, "divergence": null, "adjustment_reason": "No market odds available"}, {"horse": "Corsican Caper", "model_probability": 0.1, "market_implied_probability": null, "divergence": null, "adjustment_reason": "Noted with 10/1 each-way odds, 'not discounted'"}, {"horse": "Its Party Time", "model_probability": 0.05, "market_implied_probability": null, "divergence": null, "adjustment_reason": "No market odds available"}], "model_confidence_flag": "Medium", "calibration_notes": ["Partial market sentiment available", "Very strong support for Count Of Vendome"]}}}
