{"race_id": "Limerick_1614_20260312", "meta": {"track": "Limerick", "time": "16:14", "date": "2026-03-12", "race_name": "Party Time Handicap Chase", "class": "", "going": "Heavy", "distance": "2m6f170y", "prize": "\u20ac5,900"}, "analysis": {"ruby": {"race_id": "Limerick_1614_20260312", "rankings": [{"name": "Snow Punt", "win_probability": 0.25, "place_probability": 0.55, "fair_odds": 4.0, "key_positive_factors": ["Highest RPR (108)", "Promising Cork beginners' chase second", "Potential for improvement"], "key_risks": ["Stamina concern in heavy ground", "0-13 under rules"]}, {"name": "Duffys Hodey", "win_probability": 0.2, "place_probability": 0.5, "fair_odds": 5.0, "key_positive_factors": ["Course and distance winner", "Upward profile", "18lb below hurdle mark"], "key_risks": ["Inconsistent recent form", "Tame recent run"]}, {"name": "Aleish Lass", "win_probability": 0.15, "place_probability": 0.45, "fair_odds": 6.67, "key_positive_factors": ["Course and distance hurdle winner", "Improving recent form", "Young horse"], "key_risks": ["Limited chase experience", "Moderate recent performances"]}, {"name": "Decimation", "win_probability": 0.1, "place_probability": 0.35, "fair_odds": 10.0, "key_positive_factors": ["Course and distance second at Christmas", "Cheekpieces back on"], "key_risks": ["No chase wins", "Fading in recent races"]}, {"name": "Rideau Canal", "win_probability": 0.08, "place_probability": 0.3, "fair_odds": 12.5, "key_positive_factors": ["Recent maiden chase win", "Beat Nolans Rocco", "Soft-to-heavy ground"], "key_risks": ["Limited chase experience", "Low official rating"]}, {"name": "Difficult Decision", "win_probability": 0.07, "place_probability": 0.25, "fair_odds": 14.29, "key_positive_factors": ["Course and distance winner", "Yard returning to form"], "key_risks": ["Aging (13 years old)", "Recent poor performances"]}, {"name": "God Help Us", "win_probability": 0.05, "place_probability": 0.2, "fair_odds": 20.0, "key_positive_factors": ["Goes well fresh", "Trip and ground to suit"], "key_risks": ["Limited recent runs", "Moderate form"]}, {"name": "Nolans Rocco", "win_probability": 0.04, "place_probability": 0.15, "fair_odds": 25.0, "key_positive_factors": ["Promising recent run", "Talented rider", "9lb better off"], "key_risks": ["Maiden under rules", "Limited proven ability"]}, {"name": "Another Ocana", "win_probability": 0.03, "place_probability": 0.1, "fair_odds": 33.0, "key_positive_factors": ["Previous course wins", "Recent improvement"], "key_risks": ["Long losing sequence", "Higher mark"]}, {"name": "Ferdia", "win_probability": 0.02, "place_probability": 0.08, "fair_odds": 50.0, "key_positive_factors": ["Recently returned from long break"], "key_risks": ["Pulled up in 4 of 5 recent runs", "Wants better ground"]}, {"name": "Ishan", "win_probability": 0.01, "place_probability": 0.05, "fair_odds": 100.0, "key_positive_factors": ["Previous course wins on heavy", "New headgear"], "key_risks": ["Pulled up recently", "Limited recent form"]}, {"name": "Mastermind", "win_probability": 0.01, "place_probability": 0.05, "fair_odds": 100.0, "key_positive_factors": ["Placed in recent race", "Claiming rider"], "key_risks": ["0-12 over fences", "Limited ability"]}]}, "keenan": {"most_probable_winner": {"horse": "Snow Punt", "probability": 0.25}, "forecast_top_3": [{"combination": "Snow Punt > Duffys Hodey", "probability": 0.18}, {"combination": "Snow Punt > Aleish Lass", "probability": 0.15}], "tricast_top_3": [{"combination": "Snow Punt > Duffys Hodey > Aleish Lass", "probability": 0.11}], "pace_analysis": {"type": "MODERATE", "leader": "Decimation", "insight": "Decimation's early pace setting could create tactical challenges for stamina-challenged horses on the heavy ground"}}, "mordin": {"race_id": "Limerick_1614_20260312", "market_comparison": [{"horse": "Snow Punt", "model_probability": 0.25, "market_implied_probability": null, "divergence": null, "adjustment_reason": "No market odds available"}, {"horse": "Duffys Hodey", "model_probability": 0.2, "market_implied_probability": null, "divergence": null, "adjustment_reason": "Mixed performance with jockey concerns, potential downgrade"}, {"horse": "Aleish Lass", "model_probability": 0.15, "market_implied_probability": null, "divergence": null, "adjustment_reason": "Non-runner due to nasal discharge, significant downgrade"}, {"horse": "Decimation", "model_probability": 0.1, "market_implied_probability": null, "divergence": null, "adjustment_reason": "No market odds available"}, {"horse": "Rideau Canal", "model_probability": 0.08, "market_implied_probability": null, "divergence": null, "adjustment_reason": "No market odds available"}, {"horse": "Difficult Decision", "model_probability": 0.07, "market_implied_probability": null, "divergence": null, "adjustment_reason": "No market odds available"}, {"horse": "God Help Us", "model_probability": 0.05, "market_implied_probability": null, "divergence": null, "adjustment_reason": "No market odds available"}, {"horse": "Nolans Rocco", "model_probability": 0.04, "market_implied_probability": null, "divergence": null, "adjustment_reason": "No market odds available"}, {"horse": "Another Ocana", "model_probability": 0.03, "market_implied_probability": null, "divergence": null, "adjustment_reason": "No market odds available"}, {"horse": "Ferdia", "model_probability": 0.02, "market_implied_probability": null, "divergence": null, "adjustment_reason": "No market odds available"}, {"horse": "Ishan", "model_probability": 0.01, "market_implied_probability": null, "divergence": null, "adjustment_reason": "No market odds available"}, {"horse": "Mastermind", "model_probability": 0.01, "market_implied_probability": null, "divergence": null, "adjustment_reason": "No market odds available"}], "model_confidence_flag": "Low", "calibration_notes": ["Significant changes with Aleish Lass non-runner", "Limited market intelligence"]}}}
